{
  "kind": "collectionType",
  "collectionName": "lessons",
  "info": {
    "singularName": "lesson",
    "pluralName": "lessons",
    "displayName": "Lesson",
    "description": ""
  },
  "options": {
    "draftAndPublish": true
  },
  "pluginOptions": {
    "i18n": {
      "localized": true
    }
  },
  "attributes": {
    "Title": {
      "pluginOptions": {
        "i18n": {
          "localized": true
        }
      },
      "type": "string",
      "required": true,
      "unique": true
    },
    "Description": {
      "pluginOptions": {
        "i18n": {
          "localized": true
        }
      },
      "type": "text",
      "required": true
    },
    "Content": {
      "pluginOptions": {
        "i18n": {
          "localized": true
        }
      },
      "type": "dynamiczone",
      "components": [
        "course.media",
        "course.paragraph"
      ]
    },
    "topics": {
      "type": "relation",
      "relation": "oneToMany",
      "target": "api::topic.topic",
      "mappedBy": "lesson"
    },
    "course": {
      "type": "relation",
      "relation": "manyToOne",
      "target": "api::course.course",
      "inversedBy": "lessons"
    },
    "quizzes": {
      "type": "relation",
      "relation": "oneToMany",
      "target": "api::quiz.quiz",
      "mappedBy": "lesson"
    },
    "user_lesson_states": {
      "type": "relation",
      "relation": "oneToMany",
      "target": "api::user-lesson-state.user-lesson-state",
      "mappedBy": "lesson"
    }
  }
}
